arxiv_mcp_server/__init__.py
arxiv_mcp_server/arxiv_client.py
arxiv_mcp_server/pdf_parser.py
arxiv_mcp_server/server.py
arxiv_mcp_server/storage.py
arxiv_paper_mcp_server-0.1.2.dist-info/METADATA
arxiv_paper_mcp_server-0.1.2.dist-info/WHEEL
arxiv_paper_mcp_server-0.1.2.dist-info/entry_points.txt
arxiv_paper_mcp_server-0.1.2.dist-info/licenses/LICENSE
arxiv_paper_mcp_server-0.1.2.dist-info/RECORD
