Metadata-Version: 2.4
Name: arxiv-paper-mcp-server
Version: 0.1.2
Summary: MCP Server for searching and reading arXiv papers
Project-URL: Homepage, https://github.com/AnnaSuSu/arxiv-mcp
Project-URL: Repository, https://github.com/AnnaSuSu/arxiv-mcp
Author: aari
License-Expression: MIT
License-File: LICENSE
Keywords: arxiv,claude,llm,mcp,papers,research
Classifier: Development Status :: 4 - Beta
Classifier: Intended Audience :: Developers
Classifier: Intended Audience :: Science/Research
Classifier: License :: OSI Approved :: MIT License
Classifier: Programming Language :: Python :: 3
Classifier: Programming Language :: Python :: 3.10
Classifier: Programming Language :: Python :: 3.11
Classifier: Programming Language :: Python :: 3.12
Requires-Python: >=3.10
Requires-Dist: arxiv>=2.0.0
Requires-Dist: mcp>=1.0.0
Requires-Dist: pymupdf>=1.24.0
